{
    "playlist_id": "PLp4G6oBUcv8w8ujRtP5BtvJe8PXBwiTdl",
    "category": "tier_list",
    "video_id": "kIXcoivzGf8",
    "title": "The Best & Worst QUAD Exercises (Ranked Using Science)",
    "published_date": "2024-07-15T12:18:52Z",
    "video_url": "https://www.youtube.com/watch?v=kIXcoivzGf8",
    "thumbnail_img": "https://i.ytimg.com/vi/kIXcoivzGf8/default.jpg",
    "exercises_summaary": {
        "exercise_rankings": {
            "S-Tier": [
                {
                    "exercise_name": "Barbell Back Squat",
                    "setup_notes": "Position the barbell on your upper traps.",
                    "execution_notes": "Lock in your bar path, squat down deep, and stand back up.",
                    "tier_reasons": "High quad tension, feels good, excellent for progressive overload.",
                    "targeted_muscles": [
                        "Quadriceps"
                    ],
                    "targeted_muscle_parts": "All heads, with less emphasis on rectus femoris.",
                    "limitations": "Requires spinal stabilization.",
                    "alternative_options": "None",
                    "scientific_insights": "Studies show solid rectus femoris growth despite anatomical concerns.",
                    "additional_notes": "Include another exercise to fully engage rectus femoris."
                },
                {
                    "exercise_name": "Hack Squat",
                    "setup_notes": "Position yourself on the hack squat machine.",
                    "execution_notes": "Squat down and up with a controlled motion.",
                    "tier_reasons": "High quad tension, less setup, more direct quad tension.",
                    "targeted_muscles": [
                        "Quadriceps"
                    ],
                    "targeted_muscle_parts": "All heads, with emphasis on vastus medialis and lateralis.",
                    "limitations": "None",
                    "alternative_options": "None",
                    "scientific_insights": "Free weights and machines build muscle equally if sets are pushed hard.",
                    "additional_notes": "Use yoga blocks if full depth is not achievable."
                },
                {
                    "exercise_name": "Pendulum Squat",
                    "setup_notes": "Position yourself on the pendulum squat machine.",
                    "execution_notes": "Squat down and up following the arc path.",
                    "tier_reasons": "Natural resistance path, high quad tension.",
                    "targeted_muscles": [
                        "Quadriceps"
                    ],
                    "targeted_muscle_parts": "All heads, with emphasis on vastus medialis and lateralis.",
                    "limitations": "Rare equipment.",
                    "alternative_options": "None",
                    "scientific_insights": "None",
                    "additional_notes": "None"
                },
                {
                    "exercise_name": "Smith Machine Squat",
                    "setup_notes": "Position the bar on your upper traps in the Smith machine.",
                    "execution_notes": "Squat down and up with a controlled motion.",
                    "tier_reasons": "High quad tension, safe for pushing to failure.",
                    "targeted_muscles": [
                        "Quadriceps"
                    ],
                    "targeted_muscle_parts": "All heads, with emphasis on vastus medialis and lateralis.",
                    "limitations": "Reduced stabilizer involvement.",
                    "alternative_options": "None",
                    "scientific_insights": "None",
                    "additional_notes": "None"
                },
                {
                    "exercise_name": "Bulgarian Split Squat",
                    "setup_notes": "Position one foot on a bench behind you.",
                    "execution_notes": "Squat down with the front leg, keeping the torso upright.",
                    "tier_reasons": "High quad stretch, unilateral benefits.",
                    "targeted_muscles": [
                        "Quadriceps"
                    ],
                    "targeted_muscle_parts": "All heads, with emphasis on vastus medialis and lateralis.",
                    "limitations": "Fatiguing and psychologically challenging.",
                    "alternative_options": "None",
                    "scientific_insights": "None",
                    "additional_notes": "Limit to two sets per workout due to fatigue."
                }
            ],
            "A-Tier": [
                {
                    "exercise_name": "Barbell Front Squat",
                    "setup_notes": "Position the barbell in front of your neck.",
                    "execution_notes": "Use a two-finger grip, cross-arm grip, or strap grip. Keep elbows up, squat down, and stand up with a tall chest.",
                    "tier_reasons": "More quad tension than back squat, but awkward for some.",
                    "targeted_muscles": [
                        "Quadriceps"
                    ],
                    "targeted_muscle_parts": "All heads, with more emphasis on vastus medialis and lateralis.",
                    "limitations": "Awkward bar position for some.",
                    "alternative_options": "None",
                    "scientific_insights": "None",
                    "additional_notes": "Can be bumped to S-Tier if comfortable."
                },
                {
                    "exercise_name": "Low Bar Back Squat",
                    "setup_notes": "Position the barbell on your rear delts.",
                    "execution_notes": "Squat down and up with a controlled motion.",
                    "tier_reasons": "High quad activity, but shifts tension to glutes.",
                    "targeted_muscles": [
                        "Quadriceps",
                        "Glutes"
                    ],
                    "targeted_muscle_parts": "All heads, with less emphasis on rectus femoris.",
                    "limitations": "Shifts tension to glutes.",
                    "alternative_options": "None",
                    "scientific_insights": "None",
                    "additional_notes": "None"
                },
                {
                    "exercise_name": "45° Leg Press",
                    "setup_notes": "Position yourself on the leg press machine.",
                    "execution_notes": "Press the platform away with your feet.",
                    "tier_reasons": "High quad tension, but limited range of motion.",
                    "targeted_muscles": [
                        "Quadriceps"
                    ],
                    "targeted_muscle_parts": "All heads, with emphasis on vastus medialis and lateralis.",
                    "limitations": "Limited range of motion.",
                    "alternative_options": "None",
                    "scientific_insights": "None",
                    "additional_notes": "None"
                },
                {
                    "exercise_name": "Leg Extension",
                    "setup_notes": "Position yourself on the leg extension machine.",
                    "execution_notes": "Extend your legs fully.",
                    "tier_reasons": "Engages all four heads, especially rectus femoris.",
                    "targeted_muscles": [
                        "Quadriceps"
                    ],
                    "targeted_muscle_parts": "All heads, with emphasis on rectus femoris.",
                    "limitations": "Limited overload potential.",
                    "alternative_options": "None",
                    "scientific_insights": "Study shows more rectus femoris growth with seat back position.",
                    "additional_notes": "Include in leg days for balanced quad development."
                },
                {
                    "exercise_name": "Reverse Nordic",
                    "setup_notes": "Kneel on the ground.",
                    "execution_notes": "Lean back while keeping your body straight.",
                    "tier_reasons": "High quad stretch, accessible.",
                    "targeted_muscles": [
                        "Quadriceps"
                    ],
                    "targeted_muscle_parts": "All heads, with emphasis on rectus femoris.",
                    "limitations": "Hard to overload with weight.",
                    "alternative_options": "None",
                    "scientific_insights": "None",
                    "additional_notes": "Can be awkward for some."
                }
            ],
            "B-Tier": [
                {
                    "exercise_name": "Lunge",
                    "setup_notes": "Stand with feet together.",
                    "execution_notes": "Step forward and lower your body.",
                    "tier_reasons": "Better glute builder, moderate quad tension.",
                    "targeted_muscles": [
                        "Quadriceps",
                        "Glutes"
                    ],
                    "targeted_muscle_parts": "All heads, with more emphasis on glutes.",
                    "limitations": "Less quad tension compared to glutes.",
                    "alternative_options": "Shallow steps for more quad involvement.",
                    "scientific_insights": "None",
                    "additional_notes": "Best thought of as a glute builder."
                },
                {
                    "exercise_name": "Goblet Squat",
                    "setup_notes": "Hold a dumbbell in front of your chest.",
                    "execution_notes": "Squat down and up with a controlled motion.",
                    "tier_reasons": "High quad activation, but hard to overload.",
                    "targeted_muscles": [
                        "Quadriceps"
                    ],
                    "targeted_muscle_parts": "All heads, with emphasis on vastus medialis and lateralis.",
                    "limitations": "Limited to high rep sets.",
                    "alternative_options": "None",
                    "scientific_insights": "None",
                    "additional_notes": "Useful for beginners and as a finisher."
                },
                {
                    "exercise_name": "Sissy Squat",
                    "setup_notes": "Stand with feet shoulder-width apart.",
                    "execution_notes": "Lean back onto your toes and squat down.",
                    "tier_reasons": "High quad stretch, but awkward for some.",
                    "targeted_muscles": [
                        "Quadriceps"
                    ],
                    "targeted_muscle_parts": "All heads, with emphasis on vastus medialis and lateralis.",
                    "limitations": "Hard to load, learning curve.",
                    "alternative_options": "None",
                    "scientific_insights": "None",
                    "additional_notes": "Best for deep quad stretch."
                }
            ],
            "C-Tier": [
                {
                    "exercise_name": "Horizontal Leg Press",
                    "setup_notes": "Position yourself on the horizontal leg press machine.",
                    "execution_notes": "Press the platform away with your feet.",
                    "tier_reasons": "Limited range of motion, max out machine easily.",
                    "targeted_muscles": [
                        "Quadriceps"
                    ],
                    "targeted_muscle_parts": "All heads, with emphasis on vastus medialis and lateralis.",
                    "limitations": "Limited range of motion, overload potential.",
                    "alternative_options": "None",
                    "scientific_insights": "None",
                    "additional_notes": "None"
                },
                {
                    "exercise_name": "Deadlift",
                    "setup_notes": "Stand with feet hip-width apart.",
                    "execution_notes": "Lift the barbell from the ground to hip level.",
                    "tier_reasons": "Low quad activation, better for glutes.",
                    "targeted_muscles": [
                        "Quadriceps",
                        "Glutes"
                    ],
                    "targeted_muscle_parts": "All heads, with more emphasis on glutes.",
                    "limitations": "Low quad activation.",
                    "alternative_options": "Sumo stance for more quad involvement.",
                    "scientific_insights": "None",
                    "additional_notes": "Better for overall strength and glute building."
                },
                {
                    "exercise_name": "Step-Up",
                    "setup_notes": "Stand in front of a step or bench.",
                    "execution_notes": "Step up onto the bench with one leg.",
                    "tier_reasons": "Less quad stretch, less stable.",
                    "targeted_muscles": [
                        "Quadriceps",
                        "Glutes"
                    ],
                    "targeted_muscle_parts": "All heads, with more emphasis on glutes.",
                    "limitations": "Less stable, less quad stretch.",
                    "alternative_options": "None",
                    "scientific_insights": "None",
                    "additional_notes": "Solid glute stimulus."
                },
                {
                    "exercise_name": "Pistol Squat",
                    "setup_notes": "Stand on one leg.",
                    "execution_notes": "Squat down on one leg while keeping the other leg extended.",
                    "tier_reasons": "Impressive but limited stability and overload.",
                    "targeted_muscles": [
                        "Quadriceps"
                    ],
                    "targeted_muscle_parts": "All heads, with emphasis on vastus medialis and lateralis.",
                    "limitations": "Limited stability and overload.",
                    "alternative_options": "None",
                    "scientific_insights": "None",
                    "additional_notes": "Great for bodyweight training."
                }
            ],
            "F-Tier": [
                {
                    "exercise_name": "Squat Combination Exercises",
                    "setup_notes": "None",
                    "execution_notes": "None",
                    "tier_reasons": "Upper body fatigues before quads.",
                    "targeted_muscles": [
                        "Quadriceps"
                    ],
                    "targeted_muscle_parts": "All heads.",
                    "limitations": "Upper body fatigue.",
                    "alternative_options": "None",
                    "scientific_insights": "None",
                    "additional_notes": "None"
                },
                {
                    "exercise_name": "Bosu Ball Squat",
                    "setup_notes": "None",
                    "execution_notes": "None",
                    "tier_reasons": "Unstable, limits quad tension.",
                    "targeted_muscles": [
                        "Quadriceps"
                    ],
                    "targeted_muscle_parts": "All heads.",
                    "limitations": "Unstable.",
                    "alternative_options": "None",
                    "scientific_insights": "None",
                    "additional_notes": "None"
                },
                {
                    "exercise_name": "Jump Squat",
                    "setup_notes": "None",
                    "execution_notes": "None",
                    "tier_reasons": "Better options for muscle building.",
                    "targeted_muscles": [
                        "Quadriceps"
                    ],
                    "targeted_muscle_parts": "All heads.",
                    "limitations": "Limited tension and overload.",
                    "alternative_options": "None",
                    "scientific_insights": "None",
                    "additional_notes": "None"
                }
            ]
        }
    },
    "main_knowledge_summary": {
    
        "muscle_group": [
            "Quadriceps"
        ],
        "criterias": [
            "High quad tension, especially in the stretched position",
            "The exercise should maximize tension on the quads, particularly when they are in a stretched position.",
            "Feels good",
            "The exercise should not cause knee pain and should have a smooth resistance profile.",
            "Simple progression",
            "The exercise should allow for easy application of progressive overload, such as adding weight or reps weekly."
        ],
        "muscle_part_anatomy_function": [
            {
                "Vastus Medialis": "Located on the inside of the thigh, known as the teardrop muscle."
            },
            {
                "Vastus Intermedius": "Runs down the middle of the thigh."
            },
            {
                "Vastus Lateralis": "Located on the outside of the thigh."
            },
            {
                "Rectus Femoris": "A long, flat head that runs down the middle on top of the other heads, responsible for knee extension and hip flexion."
            }
        ],
        "form_details": "For exercises like the barbell back squat, ensure a proper bar path and maintain a stable posture. In front squats, use a grip that feels comfortable, such as the two-finger grip, crossed arm grip, or strap grip, and focus on keeping elbows up. In low bar squats, the barbell is placed on the rear delts, shifting some tension to the glutes. For Smith machine squats, the movement pattern is similar to free weight squats but with reduced stabilizer involvement. In leg extensions, setting the seat back can increase rectus femoris engagement.",
        "training_keys": "To effectively train the quadriceps, include exercises that provide high tension in the stretched position, such as squats and leg presses. Incorporate a variety of squat types to target different aspects of the quads. Ensure exercises feel comfortable and do not cause knee pain. Use progressive overload techniques to enhance muscle growth. Include exercises like leg extensions to fully engage the rectus femoris.",
        "research_insights": "Research indicates that free weights and machines can build muscle equally well if sets are pushed hard. Studies show solid rectus femoris growth with squats, despite anatomical concerns. A new study found more overall quad growth with the seat back leg extension position, likely due to increased rectus femoris stretch.",
        "optimization_notes": "To optimize quad workouts, focus on exercises that allow for deep stretches, such as hack squats and pendulum squats. Use variations like the Smith machine squat to safely push quads to failure. For exercises like the hack squat, use yoga blocks to achieve full depth if necessary. Balance exercises that target all four heads of the quadriceps for comprehensive development."
    }
}
